mcp9600/__init__.py
mcp9600-0.0.4.dist-info/LICENSE.txt
mcp9600-0.0.4.dist-info/METADATA
mcp9600-0.0.4.dist-info/WHEEL
mcp9600-0.0.4.dist-info/top_level.txt
mcp9600-0.0.4.dist-info/RECORD
